Metadata-Version: 2.1
Name: hookcheck
Version: 1.0.0
Summary: Method decorators to verify webhooks in Flask.
Home-page: https://github.com/chrisgavin/hookcheck/
License: UNKNOWN
Platform: UNKNOWN
Classifier: Programming Language :: Python :: 3
Classifier: Programming Language :: Python :: 3.5
Classifier: Programming Language :: Python :: 3.6
Classifier: Programming Language :: Python :: 3 :: Only
Requires-Python: >=3.5
Provides-Extra: dev
